MANIFEST.in
README.rst
requirements.txt
setup.cfg
setup.py
dj_diabetes/__init__.py
dj_diabetes/admin.py
dj_diabetes/apps.py
dj_diabetes/settings.py
dj_diabetes/tools.py
dj_diabetes/urls.py
dj_diabetes/wsgi.py
dj_diabetes.egg-info/PKG-INFO
dj_diabetes.egg-info/SOURCES.txt
dj_diabetes.egg-info/dependency_links.txt
dj_diabetes.egg-info/requires.txt
dj_diabetes.egg-info/top_level.txt
dj_diabetes/forms/__init__.py
dj_diabetes/forms/appointments.py
dj_diabetes/forms/base.py
dj_diabetes/forms/exams.py
dj_diabetes/forms/exercises.py
dj_diabetes/forms/glucoses.py
dj_diabetes/forms/issues.py
dj_diabetes/forms/meals.py
dj_diabetes/forms/weights.py
dj_diabetes/migrations/0001_initial.py
dj_diabetes/migrations/__init__.py
dj_diabetes/models/__init__.py
dj_diabetes/models/appointments.py
dj_diabetes/models/exams.py
dj_diabetes/models/foods.py
dj_diabetes/models/glucoses.py
dj_diabetes/models/issues.py
dj_diabetes/models/meals.py
dj_diabetes/models/sports.py
dj_diabetes/models/weights.py
dj_diabetes/static/css/diabetes.css
dj_diabetes/static/css/datepicker/datepicker.css
dj_diabetes/static/images/glyphicons_003_user.png
dj_diabetes/static/images/glyphicons_061_keynote.png
dj_diabetes/static/js/datepicker/bootstrap-datepicker.js
dj_diabetes/static/js/highcharts/highcharts.js
dj_diabetes/static/js/highcharts/modules/exporting.js
dj_diabetes/templates/base.html
dj_diabetes/templates/dj_diabetes/appointments_form.html
dj_diabetes/templates/dj_diabetes/confirm_delete.html
dj_diabetes/templates/dj_diabetes/exams_form.html
dj_diabetes/templates/dj_diabetes/exercises_form.html
dj_diabetes/templates/dj_diabetes/glucoses_form.html
dj_diabetes/templates/dj_diabetes/issues_form.html
dj_diabetes/templates/dj_diabetes/meals_form.html
dj_diabetes/templates/dj_diabetes/userprofile_form.html
dj_diabetes/templates/dj_diabetes/weights_form.html
dj_diabetes/templates/registration/login.html
dj_diabetes/templatetags/__init__.py
dj_diabetes/templatetags/dj_diabetes_extras.py
dj_diabetes/tests/__init__.py
dj_diabetes/tests/test_appointments.py
dj_diabetes/tests/test_exams.py
dj_diabetes/tests/test_foods.py
dj_diabetes/tests/test_glucoses.py
dj_diabetes/tests/test_issues.py
