Metadata-Version: 1.1
Name: dj-diabetes
Version: 0.3.1
Summary: Django Diabetes is a personal Glucose Manager
Home-page: https://github.com/push-things/dj-diabetes
Author: FoxMaSk
Author-email: foxmask@trigger-happy.eu
License: UNKNOWN
Download-URL: https://github.com/push-things/dj-diabetes/archive/dj-diabetes-0.3.1.zip
Platform: UNKNOWN
Classifier: Development Status :: 5 - Production/Stable
Classifier: Environment :: Web Environment
Classifier: Intended Audience :: Developers
Classifier: Intended Audience :: End Users/Desktop
Classifier: License :: OSI Approved :: BSD License
Classifier: Operating System :: OS Independent
Classifier: Programming Language :: Python
Classifier: Programming Language :: Python :: 3.6
Classifier: Framework :: Django
Classifier: Topic :: Database
Classifier: Topic :: Scientific/Engineering :: Medical Science Apps.
